parsedat_bedrock/__init__.py
parsedat_bedrock/__main__.py
parsedat_bedrock/parser.py
parsedat_bedrock-1.0.0.dist-info/METADATA
parsedat_bedrock-1.0.0.dist-info/WHEEL
parsedat_bedrock-1.0.0.dist-info/entry_points.txt
parsedat_bedrock-1.0.0.dist-info/RECORD
