Metadata-Version: 2.3
Name: parsedat-bedrock
Version: 1.0.0
Summary: Lightweight Little-Endian NBT -> JSON CLI utility for Minecraft Bedrock level.dat files
Author: DJ Stomp
Author-email: 85457381+DJStompZone@users.noreply.github.com
Requires-Python: >=3.11,<4.0
Classifier: Programming Language :: Python :: 3
Classifier: Programming Language :: Python :: 3.11
Classifier: Programming Language :: Python :: 3.12
Classifier: Programming Language :: Python :: 3.13
